AUTHORS
Changelog
LICENSE
MANIFEST.in
README.rst
pyproject.toml
requirements.txt
setup.py
docs/AUTHORS.rst
docs/CLI.rst
docs/Changelog.rst
docs/DEVGUIDE.rst
docs/EXAMPLES.rst
docs/INTERNAL.rst
docs/LICENSE.rst
docs/MANUAL.rst
docs/Makefile
docs/SUPPORT.rst
docs/TUTORIAL.rst
docs/conf.py
docs/index.rst
omp/__init__.py
pythran/__init__.py
pythran/backend.py
pythran/config.py
pythran/conversion.py
pythran/cxxgen.py
pythran/cxxtypes.py
pythran/dist.py
pythran/errors.py
pythran/frontend.py
pythran/graph.py
pythran/interval.py
pythran/intrinsic.py
pythran/log.py
pythran/magic.py
pythran/metadata.py
pythran/middlend.py
pythran/openmp.py
pythran/passmanager.py
pythran/pythran-darwin.cfg
pythran/pythran-default.cfg
pythran/pythran-linux.cfg
pythran/pythran-linux2.cfg
pythran/pythran-win32.cfg
pythran/pythran.cfg
pythran/run.py
pythran/spec.py
pythran/syntax.py
pythran/tables.py
pythran/toolchain.py
pythran/typing.py
pythran/unparse.py
pythran/utils.py
pythran/version.py
pythran.egg-info/PKG-INFO
pythran.egg-info/SOURCES.txt
pythran.egg-info/dependency_links.txt
pythran.egg-info/entry_points.txt
pythran.egg-info/requires.txt
pythran.egg-info/top_level.txt
pythran/analyses/__init__.py
pythran/analyses/aliases.py
pythran/analyses/ancestors.py
pythran/analyses/argument_effects.py
pythran/analyses/argument_read_once.py
pythran/analyses/ast_matcher.py
pythran/analyses/cfg.py
pythran/analyses/constant_expressions.py
pythran/analyses/dependencies.py
pythran/analyses/extended_syntax_check.py
pythran/analyses/fixed_size_list.py
pythran/analyses/global_declarations.py
pythran/analyses/global_effects.py
pythran/analyses/globals_analysis.py
pythran/analyses/has_return.py
pythran/analyses/identifiers.py
pythran/analyses/immediates.py
pythran/analyses/imported_ids.py
pythran/analyses/inlinable.py
pythran/analyses/intrinsics.py
pythran/analyses/is_assigned.py
pythran/analyses/lazyness_analysis.py
pythran/analyses/literals.py
pythran/analyses/local_declarations.py
pythran/analyses/locals_analysis.py
pythran/analyses/node_count.py
pythran/analyses/optimizable_comprehension.py
pythran/analyses/ordered_global_declarations.py
pythran/analyses/parallel_maps.py
