Metadata-Version: 2.1
Name: pythran
Version: 0.16.0
Summary: Ahead of Time compiler for numeric kernels
Author-email: Serge Guelton <serge.guelton@telecom-bretagne.eu>
License: Copyright (c) 2012, HPC Project and Serge Guelton
Project-URL: Homepage, https://github.com/serge-sans-paille/pythran
Project-URL: Documentation, https://pythran.readthedocs.io
Project-URL: Changelog, https://pythran.readthedocs.io/en/latest/Changelog.html
Classifier: Development Status :: 4 - Beta
Classifier: Environment :: Console
Classifier: Intended Audience :: Developers
Classifier: License :: OSI Approved :: BSD License
Classifier: Natural Language :: English
Classifier: Operating System :: POSIX :: Linux
Classifier: Operating System :: MacOS
Classifier: Programming Language :: Python :: 3
Classifier: Programming Language :: Python :: Implementation :: CPython
Classifier: Programming Language :: C++
Classifier: Topic :: Software Development :: Compilers
Classifier: Topic :: Software Development :: Code Generators
Requires-Python: >=3.7
License-File: LICENSE
License-File: AUTHORS
Requires-Dist: ply>=3.4
Requires-Dist: setuptools
Requires-Dist: gast~=0.5.0
Requires-Dist: numpy
Requires-Dist: beniget~=0.4.0
Provides-Extra: doc
Requires-Dist: numpy; extra == "doc"
Requires-Dist: nbsphinx; extra == "doc"
Requires-Dist: scipy; extra == "doc"
Requires-Dist: guzzle_sphinx_theme; extra == "doc"
Provides-Extra: test
Requires-Dist: ipython; extra == "test"
Requires-Dist: nbval; extra == "test"
Requires-Dist: cython; extra == "test"
Requires-Dist: wheel; extra == "test"
Requires-Dist: packaging; extra == "test"
